{"data": [{"id": 822, "ad": "AYANCIK", "takbisId": null, "ilId": 79}, {"id": 823, "ad": "BOYABAT", "takbisId": null, "ilId": 79}, {"id": 824, "ad": "DİKMEN", "takbisId": null, "ilId": 79}, {"id": 825, "ad": "DURAĞAN", "takbisId": null, "ilId": 79}, {"id": 826, "ad": "ERFELEK", "takbisId": null, "ilId": 79}, {"id": 827, "ad": "GERZE", "takbisId": null, "ilId": 79}, {"id": 829, "ad": "MERKEZ", "takbisId": null, "ilId": 79}, {"id": 828, "ad": "SARAYDÜZÜ", "takbisId": null, "ilId": 79}, {"id": 830, "ad": "TÜRKELİ", "takbisId": null, "ilId": 79}], "hasError": false, "message": "", "totalItemCount": 0, "id": 0}