{"data": [{"id": 171294, "ad": "ABİDE HATUN", "ilceId": 156, "takbisId": null}, {"id": 155356, "ad": "AKÖREN", "ilceId": 156, "takbisId": null}, {"id": 155679, "ad": "AKPINAR", "ilceId": 156, "takbisId": null}, {"id": 153001, "ad": "AKSUNGUR", "ilceId": 156, "takbisId": null}, {"id": 153802, "ad": "AKTARLA", "ilceId": 156, "takbisId": null}, {"id": 155738, "ad": "ALICIK", "ilceId": 156, "takbisId": null}, {"id": 153190, "ad": "ALİŞAR", "ilceId": 156, "takbisId": null}, {"id": 151776, "ad": "AŞAĞIBÜK", "ilceId": 156, "takbisId": null}, {"id": 203598, "ad": "BAĞLARBAŞI", "ilceId": 156, "takbisId": null}, {"id": 151761, "ad": "BAHÇECİK", "ilceId": 156, "takbisId": null}, {"id": 204898, "ad": "BAHÇELİEVLER", "ilceId": 156, "takbisId": null}, {"id": 151915, "ad": "BALGÖZE", "ilceId": 156, "takbisId": null}, {"id": 151370, "ad": "BAYAT", "ilceId": 156, "takbisId": null}, {"id": 153515, "ad": "BAYAZIT", "ilceId": 156, "takbisId": null}, {"id": 156139, "ad": "BUĞDAYLI", "ilceId": 156, "takbisId": null}, {"id": 154057, "ad": "BULAK", "ilceId": 156, "takbisId": null}, {"id": 155275, "ad": "BÜYÜKÇAY", "ilceId": 156, "takbisId": null}, {"id": 158751, "ad": "CAMİCEDİT", "ilceId": 156, "takbisId": null}, {"id": 134406, "ad": "ÇAMLICA", "ilceId": 156, "takbisId": null}, {"id": 152902, "ad": "ÇAVUNDUR", "ilceId": 156, "takbisId": null}, {"id": 155117, "ad": "ÇAYBAŞI", "ilceId": 156, "takbisId": null}, {"id": 157207, "ad": "ÇAYIR", "ilceId": 156, "takbisId": null}, {"id": 153309, "ad": "ÇAYIRÖZÜ", "ilceId": 156, "takbisId": null}, {"id": 156693, "ad": "ÇOBANÖREN", "ilceId": 156, "takbisId": null}, {"id": 153216, "ad": "DEMİRPINAR", "ilceId": 156, "takbisId": null}, {"id": 153560, "ad": "DEREALAN", "ilceId": 156, "takbisId": null}, {"id": 154263, "ad": "DİPHACI", "ilceId": 156, "takbisId": null}, {"id": 155769, "ad": "ELMAYOLU", "ilceId": 156, "takbisId": null}, {"id": 151356, "ad": "ESENTEPE", "ilceId": 156, "takbisId": null}, {"id": 155075, "ad": "ESKİCAMİ", "ilceId": 156, "takbisId": null}, {"id": 153136, "ad": "EYMİR", "ilceId": 156, "takbisId": null}, {"id": 155238, "ad": "GAZİMAHBUP", "ilceId": 156, "takbisId": null}, {"id": 157208, "ad": "GELİNSİNİ", "ilceId": 156, "takbisId": null}, {"id": 158568, "ad": "GÖKÇEBAĞ", "ilceId": 156, "takbisId": null}, {"id": 154087, "ad": "GÜMÜŞTEPE", "ilceId": 156, "takbisId": null}, {"id": 155288, "ad": "HACET", "ilceId": 156, "takbisId": null}, {"id": 153111, "ad": "HACIBALI", "ilceId": 156, "takbisId": null}, {"id": 155706, "ad": "HACIHASAN", "ilceId": 156, "takbisId": null}, {"id": 153678, "ad": "HACIYAKUP", "ilceId": 156, "takbisId": null}, {"id": 155339, "ad": "HAN", "ilceId": 156, "takbisId": null}, {"id": 134091, "ad": "HARMANLAR", "ilceId": 156, "takbisId": null}, {"id": 155488, "ad": "HAYRETTİN", "ilceId": 156, "takbisId": null}, {"id": 153597, "ad": "HIRKA", "ilceId": 156, "takbisId": null}, {"id": 154916, "ad": "HOCASÜLEYMAN", "ilceId": 156, "takbisId": null}, {"id": 153679, "ad": "İNALAN", "ilceId": 156, "takbisId": null}, {"id": 155944, "ad": "KAMIŞLI", "ilceId": 156, "takbisId": null}, {"id": 156869, "ad": "KARACAKAYA", "ilceId": 156, "takbisId": null}, {"id": 158778, "ad": "KARAMAĞARA", "ilceId": 156, "takbisId": null}, {"id": 153215, "ad": "KARAMUSTAFAPAŞA", "ilceId": 156, "takbisId": null}, {"id": 153045, "ad": "KARATEPE", "ilceId": 156, "takbisId": null}, {"id": 155885, "ad": "KARŞIYAKA", "ilceId": 156, "takbisId": null}, {"id": 156338, "ad": "KAYADÜZÜ", "ilceId": 156, "takbisId": null}, {"id": 149837, "ad": "KIREYMİR", "ilceId": 156, "takbisId": null}, {"id": 155459, "ad": "KIZILEĞREK", "ilceId": 156, "takbisId": null}, {"id": 154958, "ad": "KOÇ", "ilceId": 156, "takbisId": null}, {"id": 135219, "ad": "KUYU", "ilceId": 156, "takbisId": null}, {"id": 155098, "ad": "KÜÇÜKÇAY", "ilceId": 156, "takbisId": null}, {"id": 205167, "ad": "KÜMBETHATUN", "ilceId": 156, "takbisId": null}, {"id": 155688, "ad": "MAHMUTLU", "ilceId": 156, "takbisId": null}, {"id": 156326, "ad": "MAHZEN", "ilceId": 156, "takbisId": null}, {"id": 157523, "ad": "MEHMETAKİFERSOY", "ilceId": 156, "takbisId": null}, {"id": 205482, "ad": "MUŞRUF", "ilceId": 156, "takbisId": null}, {"id": 155315, "ad": "NACCAR", "ilceId": 156, "takbisId": null}, {"id": 153539, "ad": "NUSRATİYE", "ilceId": 156, "takbisId": null}, {"id": 156492, "ad": "ORTABÜK", "ilceId": 156, "takbisId": null}, {"id": 155304, "ad": "ORTAOVA", "ilceId": 156, "takbisId": null}, {"id": 156891, "ad": "OSMANOĞLU", "ilceId": 156, "takbisId": null}, {"id": 157433, "ad": "OYMAAĞAÇ", "ilceId": 156, "takbisId": null}, {"id": 154940, "ad": "OYMAK", "ilceId": 156, "takbisId": null}, {"id": 158938, "ad": "PEKMEZCİ", "ilceId": 156, "takbisId": null}, {"id": 156325, "ad": "SARAYCIK", "ilceId": 156, "takbisId": null}, {"id": 151916, "ad": "SARIBUĞDAY", "ilceId": 156, "takbisId": null}, {"id": 155131, "ad": "SARIKÖY", "ilceId": 156, "takbisId": null}, {"id": 158939, "ad": "SAZLICA", "ilceId": 156, "takbisId": null}, {"id": 153655, "ad": "SELİMİYE", "ilceId": 156, "takbisId": null}, {"id": 158991, "ad": "SOFULAR", "ilceId": 156, "takbisId": null}, {"id": 135092, "ad": "ŞEYHYENİ", "ilceId": 156, "takbisId": null}, {"id": 157543, "ad": "TAVŞAN", "ilceId": 156, "takbisId": null}, {"id": 153609, "ad": "UZUNYAZI", "ilceId": 156, "takbisId": null}, {"id": 158387, "ad": "YAKUP", "ilceId": 156, "takbisId": null}, {"id": 156339, "ad": "YALNIZ", "ilceId": 156, "takbisId": null}, {"id": 152934, "ad": "YAYLACIK", "ilceId": 156, "takbisId": null}, {"id": 153046, "ad": "YENİCE", "ilceId": 156, "takbisId": null}, {"id": 171293, "ad": "YENİMAHALLE", "ilceId": 156, "takbisId": null}, {"id": 155505, "ad": "YEŞİLÖREN", "ilceId": 156, "takbisId": null}, {"id": 153516, "ad": "YEŞİLTEPE", "ilceId": 156, "takbisId": null}, {"id": 156532, "ad": "YOLÜSTÜ", "ilceId": 156, "takbisId": null}, {"id": 159128, "ad": "YUKARIBÜK", "ilceId": 156, "takbisId": null}, {"id": 180682, "ad": "YUNUS EMRE", "ilceId": 156, "takbisId": null}], "hasError": false, "message": "", "totalItemCount": 0, "id": 0}