{"data": [{"id": 42220, "ad": "AKBÜK", "ilceId": 210, "takbisId": null}, {"id": 42470, "ad": "AKKÖY", "ilceId": 210, "takbisId": null}, {"id": 149051, "ad": "AKYENİKÖY", "ilceId": 210, "takbisId": null}, {"id": 205968, "ad": "ALTINKUM", "ilceId": 210, "takbisId": null}, {"id": 41884, "ad": "BALAT", "ilceId": 210, "takbisId": null}, {"id": 147722, "ad": "BATNAZ", "ilceId": 210, "takbisId": null}, {"id": 205969, "ad": "CUMHURİYET", "ilceId": 210, "takbisId": null}, {"id": 205966, "ad": "ÇAMLIK", "ilceId": 210, "takbisId": null}, {"id": 42369, "ad": "DENİZKÖY", "ilceId": 210, "takbisId": null}, {"id": 169310, "ad": "DİDİM", "ilceId": 210, "takbisId": null}, {"id": 205967, "ad": "EFELER", "ilceId": 210, "takbisId": null}, {"id": 42437, "ad": "FEVZİPAŞA", "ilceId": 210, "takbisId": null}, {"id": 205965, "ad": "HİSAR", "ilceId": 210, "takbisId": null}, {"id": 205964, "ad": "MAVİŞEHİR", "ilceId": 210, "takbisId": null}, {"id": 205963, "ad": "MERSİNDERE", "ilceId": 210, "takbisId": null}, {"id": 152450, "ad": "YALIKÖY", "ilceId": 210, "takbisId": null}, {"id": 205970, "ad": "YENİ", "ilceId": 210, "takbisId": null}], "hasError": false, "message": "", "totalItemCount": 0, "id": 0}