{"data": [{"id": 48733, "ad": "ABDİÇIKMAZ", "ilceId": 148, "takbisId": null}, {"id": 46773, "ad": "ADIMOVA", "ilceId": 148, "takbisId": null}, {"id": 206900, "ad": "AKYURT", "ilceId": 148, "takbisId": null}, {"id": 48293, "ad": "ALAKOYUN", "ilceId": 148, "takbisId": null}, {"id": 141051, "ad": "AŞAĞI ALADAĞ", "ilceId": 148, "takbisId": null}, {"id": 141928, "ad": "AŞAĞI DEREDİBİ", "ilceId": 148, "takbisId": null}, {"id": 145624, "ad": "AŞAĞI GÖZLÜCE", "ilceId": 148, "takbisId": null}, {"id": 139849, "ad": "AŞAĞI KARABAL", "ilceId": 148, "takbisId": null}, {"id": 141936, "ad": "AŞAĞI YENİGÜN", "ilceId": 148, "takbisId": null}, {"id": 48466, "ad": "AYVACIK", "ilceId": 148, "takbisId": null}, {"id": 48463, "ad": "BALDERE", "ilceId": 148, "takbisId": null}, {"id": 48734, "ad": "BEKLEMEZ", "ilceId": 148, "takbisId": null}, {"id": 48723, "ad": "BUZHANE", "ilceId": 148, "takbisId": null}, {"id": 46781, "ad": "CEYLANLI", "ilceId": 148, "takbisId": null}, {"id": 48570, "ad": "ÇAĞLAYAN", "ilceId": 148, "takbisId": null}, {"id": 48556, "ad": "ÇEVRE", "ilceId": 148, "takbisId": null}, {"id": 48796, "ad": "DANAKIRAN", "ilceId": 148, "takbisId": null}, {"id": 48501, "ad": "DEMİRKAPI", "ilceId": 148, "takbisId": null}, {"id": 48329, "ad": "EKİNCİK", "ilceId": 148, "takbisId": null}, {"id": 48813, "ad": "ERDOĞAN", "ilceId": 148, "takbisId": null}, {"id": 48486, "ad": "ESENÖREN", "ilceId": 148, "takbisId": null}, {"id": 48166, "ad": "GÜLTEPE", "ilceId": 148, "takbisId": null}, {"id": 48529, "ad": "GÜMÜŞKUŞAK", "ilceId": 148, "takbisId": null}, {"id": 48614, "ad": "HATUNKOMU", "ilceId": 148, "takbisId": null}, {"id": 48320, "ad": "KAÇMAZ", "ilceId": 148, "takbisId": null}, {"id": 48806, "ad": "KALE", "ilceId": 148, "takbisId": null}, {"id": 48797, "ad": "KAMIŞLI", "ilceId": 148, "takbisId": null}, {"id": 48163, "ad": "KANDİLDAĞI", "ilceId": 148, "takbisId": null}, {"id": 48432, "ad": "KARADOĞU", "ilceId": 148, "takbisId": null}, {"id": 48188, "ad": "KARAKAZAN", "ilceId": 148, "takbisId": null}, {"id": 48433, "ad": "KARASEYİTALİ", "ilceId": 148, "takbisId": null}, {"id": 48316, "ad": "KARLICA", "ilceId": 148, "takbisId": null}, {"id": 48469, "ad": "KAYNAKLI", "ilceId": 148, "takbisId": null}, {"id": 46775, "ad": "KILIÇ", "ilceId": 148, "takbisId": null}, {"id": 144187, "ad": "KÖŞK", "ilceId": 148, "takbisId": null}, {"id": 48839, "ad": "KÜMBET", "ilceId": 148, "takbisId": null}, {"id": 140864, "ad": "MERKEZ", "ilceId": 148, "takbisId": null}, {"id": 48189, "ad": "NALLIKONAK", "ilceId": 148, "takbisId": null}, {"id": 48349, "ad": "ÖZDİREK", "ilceId": 148, "takbisId": null}, {"id": 48544, "ad": "SARIBUĞDAY", "ilceId": 148, "takbisId": null}, {"id": 48438, "ad": "SESLİDOĞAN", "ilceId": 148, "takbisId": null}, {"id": 46872, "ad": "SEYİTHANBEY", "ilceId": 148, "takbisId": null}, {"id": 47101, "ad": "SOĞANLITEPE", "ilceId": 148, "takbisId": null}, {"id": 48443, "ad": "SÜLEYMANKÜMBET", "ilceId": 148, "takbisId": null}, {"id": 48530, "ad": "TÜKENMEZ", "ilceId": 148, "takbisId": null}, {"id": 48285, "ad": "UĞURTAŞ", "ilceId": 148, "takbisId": null}, {"id": 48549, "ad": "YAPILI", "ilceId": 148, "takbisId": null}, {"id": 48515, "ad": "YENİ", "ilceId": 148, "takbisId": null}, {"id": 48545, "ad": "YOĞUNHİSAR", "ilceId": 148, "takbisId": null}, {"id": 141040, "ad": "YUKARI ALADAĞ", "ilceId": 148, "takbisId": null}, {"id": 140446, "ad": "YUKARI GÖZLÜCE", "ilceId": 148, "takbisId": null}, {"id": 144392, "ad": "YUKARI YENİGÜN", "ilceId": 148, "takbisId": null}, {"id": 48154, "ad": "YUVACIK", "ilceId": 148, "takbisId": null}], "hasError": false, "message": "", "totalItemCount": 0, "id": 0}