{"data": [{"id": 205863, "ad": "1. GÜNDOĞAN", "ilceId": 6178, "takbisId": null}, {"id": 166967, "ad": "2.AYGÖREN", "ilceId": 6178, "takbisId": null}, {"id": 166969, "ad": "2.DİNKÇİLER", "ilceId": 6178, "takbisId": null}, {"id": 205864, "ad": "2. GÜNDOĞAN", "ilceId": 6178, "takbisId": null}, {"id": 166876, "ad": "AKARSU", "ilceId": 6178, "takbisId": null}, {"id": 169547, "ad": "AKÇAKÖY", "ilceId": 6178, "takbisId": null}, {"id": 166879, "ad": "ALİAĞA", "ilceId": 6178, "takbisId": null}, {"id": 166965, "ad": "ALTIEYLÜL", "ilceId": 6178, "takbisId": null}, {"id": 166881, "ad": "ASLIHAN", "ilceId": 6178, "takbisId": null}, {"id": 166882, "ad": "ASLIHANTEPECİK", "ilceId": 6178, "takbisId": null}, {"id": 166883, "ad": "ATAKÖY", "ilceId": 6178, "takbisId": null}, {"id": 169548, "ad": "ATKÖY", "ilceId": 6178, "takbisId": null}, {"id": 166887, "ad": "AYNAOĞLU", "ilceId": 6178, "takbisId": null}, {"id": 166884, "ad": "AYŞEBACI", "ilceId": 6178, "takbisId": null}, {"id": 166885, "ad": "AYVACIK", "ilceId": 6178, "takbisId": null}, {"id": 166886, "ad": "AYVATLAR", "ilceId": 6178, "takbisId": null}, {"id": 166888, "ad": "BAĞALAN", "ilceId": 6178, "takbisId": null}, {"id": 166889, "ad": "BAHÇEDERE", "ilceId": 6178, "takbisId": null}, {"id": 205122, "ad": "BAHÇELİEVLER", "ilceId": 6178, "takbisId": null}, {"id": 169550, "ad": "BALIKLI", "ilceId": 6178, "takbisId": null}, {"id": 166890, "ad": "BAYAT", "ilceId": 6178, "takbisId": null}, {"id": 169551, "ad": "BEREKETLİ", "ilceId": 6178, "takbisId": null}, {"id": 166891, "ad": "BEŞPINAR", "ilceId": 6178, "takbisId": null}, {"id": 166893, "ad": "BİGATEPE", "ilceId": 6178, "takbisId": null}, {"id": 166895, "ad": "BOZEN", "ilceId": 6178, "takbisId": null}, {"id": 169552, "ad": "BÜYÜKBOSTANCI", "ilceId": 6178, "takbisId": null}, {"id": 166897, "ad": "CİNGE", "ilceId": 6178, "takbisId": null}, {"id": 166898, "ad": "ÇAKILLIK", "ilceId": 6178, "takbisId": null}, {"id": 166901, "ad": "ÇAMKÖY", "ilceId": 6178, "takbisId": null}, {"id": 166900, "ad": "ÇANDIR", "ilceId": 6178, "takbisId": null}, {"id": 169554, "ad": "ÇAYIRHİSAR", "ilceId": 6178, "takbisId": null}, {"id": 166902, "ad": "ÇINARLIDERE", "ilceId": 6178, "takbisId": null}, {"id": 166903, "ad": "ÇİFTÇİDERE", "ilceId": 6178, "takbisId": null}, {"id": 169583, "ad": "ÇİFTLİK", "ilceId": 6178, "takbisId": null}, {"id": 166904, "ad": "ÇORAKLIK", "ilceId": 6178, "takbisId": null}, {"id": 166905, "ad": "ÇUKURHÜSEYİN", "ilceId": 6178, "takbisId": null}, {"id": 166906, "ad": "DALLIMANDIRA", "ilceId": 6178, "takbisId": null}, {"id": 166907, "ad": "DEDEBURNU", "ilceId": 6178, "takbisId": null}, {"id": 166909, "ad": "DEREÇİFTLİK", "ilceId": 6178, "takbisId": null}, {"id": 166910, "ad": "DEREKÖY", "ilceId": 6178, "takbisId": null}, {"id": 166968, "ad": "DİNKÇİLER", "ilceId": 6178, "takbisId": null}, {"id": 166911, "ad": "DİŞBUDAK", "ilceId": 6178, "takbisId": null}, {"id": 166913, "ad": "ERTUĞRUL", "ilceId": 6178, "takbisId": null}, {"id": 166972, "ad": "GAZİOSMANPAŞA", "ilceId": 6178, "takbisId": null}, {"id": 166914, "ad": "GÖKÇEÖREN", "ilceId": 6178, "takbisId": null}, {"id": 169558, "ad": "GÖKKÖY", "ilceId": 6178, "takbisId": null}, {"id": 166868, "ad": "GÜMÜŞÇEŞME", "ilceId": 6178, "takbisId": null}, {"id": 166973, "ad": "GÜNDOĞAN", "ilceId": 6178, "takbisId": null}, {"id": 166974, "ad": "HACIİLBEY", "ilceId": 6178, "takbisId": null}, {"id": 169559, "ad": "HALALCA", "ilceId": 6178, "takbisId": null}, {"id": 205374, "ad": "HASAN BASRİ ÇANTAY", "ilceId": 6178, "takbisId": null}, {"id": 169561, "ad": "İNKAYA", "ilceId": 6178, "takbisId": null}, {"id": 169562, "ad": "KABAKLI", "ilceId": 6178, "takbisId": null}, {"id": 166919, "ad": "KARABEYLER", "ilceId": 6178, "takbisId": null}, {"id": 166920, "ad": "KARAKAVAK", "ilceId": 6178, "takbisId": null}, {"id": 169566, "ad": "KARAKAYA", "ilceId": 6178, "takbisId": null}, {"id": 166921, "ad": "KARAMAN", "ilceId": 6178, "takbisId": null}, {"id": 166922, "ad": "KARAMANLAR", "ilceId": 6178, "takbisId": null}, {"id": 205454, "ad": "KASAPLAR", "ilceId": 6178, "takbisId": null}, {"id": 169571, "ad": "K.BOSTANCI", "ilceId": 6178, "takbisId": null}, {"id": 169568, "ad": "KESİRVEN", "ilceId": 6178, "takbisId": null}, {"id": 166924, "ad": "KILCILAR", "ilceId": 6178, "takbisId": null}, {"id": 166926, "ad": "KİRAZKÖY", "ilceId": 6178, "takbisId": null}, {"id": 166927, "ad": "KİRAZPINAR", "ilceId": 6178, "takbisId": null}, {"id": 166929, "ad": "KONAKPINAR", "ilceId": 6178, "takbisId": null}, {"id": 166931, "ad": "KOZDEREGÜVEM", "ilceId": 6178, "takbisId": null}, {"id": 166930, "ad": "KOZÖREN", "ilceId": 6178, "takbisId": null}, {"id": 166932, "ad": "KÖSELER", "ilceId": 6178, "takbisId": null}, {"id": 169570, "ad": "KÖYLÜKÖY", "ilceId": 6178, "takbisId": null}, {"id": 166935, "ad": "KUŞKAYA", "ilceId": 6178, "takbisId": null}, {"id": 166933, "ad": "KUTLUDÜĞÜN", "ilceId": 6178, "takbisId": null}, {"id": 166936, "ad": "KUYUALAN", "ilceId": 6178, "takbisId": null}, {"id": 166937, "ad": "KÜPELER", "ilceId": 6178, "takbisId": null}, {"id": 166938, "ad": "KÜRSE", "ilceId": 6178, "takbisId": null}, {"id": 166939, "ad": "MACARLAR", "ilceId": 6178, "takbisId": null}, {"id": 166940, "ad": "MERYEMDERE", "ilceId": 6178, "takbisId": null}, {"id": 169555, "ad": "NERGİZ", "ilceId": 6178, "takbisId": null}, {"id": 169573, "ad": "ORHANLI", "ilceId": 6178, "takbisId": null}, {"id": 166942, "ad": "ORTAMANDIRA", "ilceId": 6178, "takbisId": null}, {"id": 166943, "ad": "OVABAYINDIR", "ilceId": 6178, "takbisId": null}, {"id": 166945, "ad": "OVAKÖY", "ilceId": 6178, "takbisId": null}, {"id": 169574, "ad": "PAMUKÇU", "ilceId": 6178, "takbisId": null}, {"id": 169575, "ad": "PAŞAKÖY", "ilceId": 6178, "takbisId": null}, {"id": 166977, "ad": "PLEVNE", "ilceId": 6178, "takbisId": null}, {"id": 166946, "ad": "SARIALAN", "ilceId": 6178, "takbisId": null}, {"id": 169576, "ad": "SELİMİYE", "ilceId": 6178, "takbisId": null}, {"id": 166947, "ad": "SIVATPINAR", "ilceId": 6178, "takbisId": null}, {"id": 166978, "ad": "SUBAY", "ilceId": 6178, "takbisId": null}, {"id": 205320, "ad": "SÜTLÜCE", "ilceId": 6178, "takbisId": null}, {"id": 169578, "ad": "TAŞKÖY", "ilceId": 6178, "takbisId": null}, {"id": 166949, "ad": "TAŞPINAR", "ilceId": 6178, "takbisId": null}, {"id": 166951, "ad": "TAYYİPLER", "ilceId": 6178, "takbisId": null}, {"id": 166953, "ad": "TURNALAR", "ilceId": 6178, "takbisId": null}, {"id": 169579, "ad": "TÜRKALİ", "ilceId": 6178, "takbisId": null}, {"id": 166956, "ad": "YAKUPKÖY", "ilceId": 6178, "takbisId": null}, {"id": 166958, "ad": "YENİCE", "ilceId": 6178, "takbisId": null}, {"id": 166961, "ad": "YEŞİLLER", "ilceId": 6178, "takbisId": null}, {"id": 205325, "ad": "YILDIZ", "ilceId": 6178, "takbisId": null}], "hasError": false, "message": "", "totalItemCount": 0, "id": 0}