{"data": [{"id": 136740, "ad": "ABACILAR", "ilceId": 492, "takbisId": null}, {"id": 138667, "ad": "AKÇAŞAR", "ilceId": 492, "takbisId": null}, {"id": 137666, "ad": "ALTIKAPI", "ilceId": 492, "takbisId": null}, {"id": 138789, "ad": "AŞAĞI KAŞIKARA", "ilceId": 492, "takbisId": null}, {"id": 140979, "ad": "AŞAĞI TIRTAR", "ilceId": 492, "takbisId": null}, {"id": 139030, "ad": "AYVALI", "ilceId": 492, "takbisId": null}, {"id": 138383, "ad": "BAĞKONAK", "ilceId": 492, "takbisId": null}, {"id": 142862, "ad": "BAĞLARBAŞI", "ilceId": 492, "takbisId": null}, {"id": 137507, "ad": "BAHTİYAR", "ilceId": 492, "takbisId": null}, {"id": 142719, "ad": "CELEPTAŞ", "ilceId": 492, "takbisId": null}, {"id": 136703, "ad": "ÇAKIRÇAL", "ilceId": 492, "takbisId": null}, {"id": 140111, "ad": "ÇAMHARMAN", "ilceId": 492, "takbisId": null}, {"id": 139515, "ad": "ÇETİNCE", "ilceId": 492, "takbisId": null}, {"id": 136791, "ad": "DEDEÇAM", "ilceId": 492, "takbisId": null}, {"id": 139306, "ad": "EĞİRLER", "ilceId": 492, "takbisId": null}, {"id": 136764, "ad": "ESKİ", "ilceId": 492, "takbisId": null}, {"id": 137329, "ad": "EYUPLAR", "ilceId": 492, "takbisId": null}, {"id": 137121, "ad": "GÖKÇEALİ", "ilceId": 492, "takbisId": null}, {"id": 140369, "ad": "GÖRGÜBAYRAM", "ilceId": 492, "takbisId": null}, {"id": 141172, "ad": "GÖRGÜCAMİ", "ilceId": 492, "takbisId": null}, {"id": 137328, "ad": "GÖRGÜORTA", "ilceId": 492, "takbisId": null}, {"id": 139031, "ad": "HİSARARDI", "ilceId": 492, "takbisId": null}, {"id": 137533, "ad": "HÜYÜKLÜ", "ilceId": 492, "takbisId": null}, {"id": 138801, "ad": "İLEĞİ", "ilceId": 492, "takbisId": null}, {"id": 140923, "ad": "KAŞAŞAĞI", "ilceId": 492, "takbisId": null}, {"id": 139082, "ad": "KAŞCAMİ", "ilceId": 492, "takbisId": null}, {"id": 139083, "ad": "KAŞHACIBEY", "ilceId": 492, "takbisId": null}, {"id": 137190, "ad": "KAŞYUKARI", "ilceId": 492, "takbisId": null}, {"id": 137734, "ad": "KIRKBAŞ", "ilceId": 492, "takbisId": null}, {"id": 139105, "ad": "KIZILCA", "ilceId": 492, "takbisId": null}, {"id": 138394, "ad": "KORUYAKA", "ilceId": 492, "takbisId": null}, {"id": 138384, "ad": "KOZLUÇAY", "ilceId": 492, "takbisId": null}, {"id": 206581, "ad": "KÖRKÜLER", "ilceId": 492, "takbisId": null}, {"id": 203075, "ad": "KÖRKÜLER(AŞAĞI)", "ilceId": 492, "takbisId": null}, {"id": 142693, "ad": "KÖRKÜLER(ESKİ)", "ilceId": 492, "takbisId": null}, {"id": 203073, "ad": "KÖRKÜLER(PAZAR)", "ilceId": 492, "takbisId": null}, {"id": 203076, "ad": "KÖRKÜLER(YENİ)", "ilceId": 492, "takbisId": null}, {"id": 142694, "ad": "KUMDANLI", "ilceId": 492, "takbisId": null}, {"id": 137864, "ad": "KURUSARI", "ilceId": 492, "takbisId": null}, {"id": 135630, "ad": "KUYUCAK", "ilceId": 492, "takbisId": null}, {"id": 139473, "ad": "LEBLEBİCİLER", "ilceId": 492, "takbisId": null}, {"id": 135612, "ad": "MISIRLI", "ilceId": 492, "takbisId": null}, {"id": 138062, "ad": "MÜDERRİS", "ilceId": 492, "takbisId": null}, {"id": 140694, "ad": "ÖZBAYAT", "ilceId": 492, "takbisId": null}, {"id": 136918, "ad": "ÖZGÜNEY", "ilceId": 492, "takbisId": null}, {"id": 142718, "ad": "PAZARAŞAĞI", "ilceId": 492, "takbisId": null}, {"id": 141306, "ad": "PAZARYUKARI", "ilceId": 492, "takbisId": null}, {"id": 141283, "ad": "SAĞIR", "ilceId": 492, "takbisId": null}, {"id": 139121, "ad": "SALUR", "ilceId": 492, "takbisId": null}, {"id": 139387, "ad": "SARAY", "ilceId": 492, "takbisId": null}, {"id": 137275, "ad": "SOFULAR", "ilceId": 492, "takbisId": null}, {"id": 137865, "ad": "SÜCÜLLÜ", "ilceId": 492, "takbisId": null}, {"id": 140352, "ad": "TABAKLAR", "ilceId": 492, "takbisId": null}, {"id": 139446, "ad": "TAŞEVİ", "ilceId": 492, "takbisId": null}, {"id": 137724, "ad": "TERZİLER", "ilceId": 492, "takbisId": null}, {"id": 139429, "ad": "TOKMACIK", "ilceId": 492, "takbisId": null}, {"id": 138361, "ad": "YAĞCILAR", "ilceId": 492, "takbisId": null}, {"id": 138709, "ad": "YARIKKAYA", "ilceId": 492, "takbisId": null}, {"id": 206635, "ad": "YUKARIKAŞIKARA", "ilceId": 492, "takbisId": null}, {"id": 137202, "ad": "YUKARI KAŞIKARA(FATİH)", "ilceId": 492, "takbisId": null}, {"id": 203074, "ad": "YUKARIKAŞIKARA(HARMAN)", "ilceId": 492, "takbisId": null}, {"id": 203077, "ad": "YUKARIKAŞIKARA(YAYLA)", "ilceId": 492, "takbisId": null}, {"id": 203078, "ad": "YUKARIKAŞIKARA(YENİ)", "ilceId": 492, "takbisId": null}, {"id": 140757, "ad": "YUKARI TIRTAR", "ilceId": 492, "takbisId": null}], "hasError": false, "message": "", "totalItemCount": 0, "id": 0}