{"data": [{"id": 15813, "ad": "ALİBEY", "ilceId": 763, "takbisId": null}, {"id": 133755, "ad": "ANBARCILI", "ilceId": 763, "takbisId": null}, {"id": 15909, "ad": "AYRILIK", "ilceId": 763, "takbisId": null}, {"id": 16867, "ad": "GÜLİSTAN", "ilceId": 763, "takbisId": null}, {"id": 152915, "ad": "GÜLYALI", "ilceId": 763, "takbisId": null}, {"id": 15708, "ad": "HOŞKÖY", "ilceId": 763, "takbisId": null}, {"id": 16729, "ad": "KESTANE", "ilceId": 763, "takbisId": null}, {"id": 15917, "ad": "MUSTAFALI", "ilceId": 763, "takbisId": null}, {"id": 16124, "ad": "SAYACA", "ilceId": 763, "takbisId": null}, {"id": 16365, "ad": "TAŞLIÇAY", "ilceId": 763, "takbisId": null}, {"id": 205141, "ad": "TEPEALTI", "ilceId": 763, "takbisId": null}, {"id": 15969, "ad": "TURNASUYU", "ilceId": 763, "takbisId": null}, {"id": 169818, "ad": "ÜRÜMBEY", "ilceId": 763, "takbisId": null}, {"id": 16457, "ad": "YENİKÖY", "ilceId": 763, "takbisId": null}], "hasError": false, "message": "", "totalItemCount": 0, "id": 0}